Metadata-Version: 2.1
Name: PrintXD
Version: 0.1
Summary: Testing Pypi upload
Home-page: https://github.com/luke9kim8/PrintXD
Download-URL: https://github.com/luke9kim8/PrintXD/archive/refs/tags/v_0.1.tar.gz
Author: Luke Kim
Author-email: luke9kim8@gmail.com
License: MIT
Platform: UNKNOWN
Classifier: Development Status :: 3 - Alpha
Classifier: Intended Audience :: Developers
Classifier: Topic :: Software Development :: Build Tools
Classifier: License :: OSI Approved :: MIT License
Classifier: Programming Language :: Python :: 3
Classifier: Programming Language :: Python :: 3.4
Classifier: Programming Language :: Python :: 3.5
Classifier: Programming Language :: Python :: 3.6
License-File: LICENSE.txt
